{"stat.walkOneCm":6821,"stat.leaveGame":4,"stat.drop.minecraft.glowstone_dust":1,"stat.damageTaken":265,"stat.useItem.minecraft.stonebrick":6,"stat.pickup.minecraft.reeds":1,"stat.useItem.minecraft.brick_block":1,"stat.flyOneCm":4752,"stat.deaths":1,"stat.pickup.minecraft.water_bucket":2,"stat.pickup.minecraft.iron_door":2,"stat.drop":1,"stat.jump":24,"stat.playOneMinute":9229,"stat.pickup.minecraft.iron_pickaxe":1,"stat.pickup.minecraft.beef":1,"stat.sneakTime":23,"stat.pickup.minecraft.glowstone_dust":2,"stat.useItem.minecraft.purpur_block":1,"stat.crouchOneCm":39,"stat.timeSinceDeath":8146,"stat.sprintOneCm":1299,"stat.pickup.minecraft.purpur_block":1,"stat.useItem.minecraft.iron_door":1}